vspec_vsm/__init__.py
vspec_vsm/config.py
vspec_vsm/coordinate_grid.py
vspec_vsm/faculae.py
vspec_vsm/flares.py
vspec_vsm/granules.py
vspec_vsm/helpers.py
vspec_vsm/spots.py
vspec_vsm/star.py
vspec_vsm/xoflares.py
vspec_vsm-0.3.7.dist-info/LICENSE
vspec_vsm-0.3.7.dist-info/METADATA
vspec_vsm-0.3.7.dist-info/WHEEL
vspec_vsm-0.3.7.dist-info/top_level.txt
vspec_vsm-0.3.7.dist-info/RECORD
