Metadata-Version: 2.1
Name: vspec-vsm
Version: 0.3.7
Summary: The VSPEC Variable Star Model as a standalone package.
Author-email: Ted Johnson <ted.johnson@unlv.edu>, Cameron Kelahan <cameron.kelahan@gmail.com>
Maintainer-email: Ted Johnson <ted.johnson@unlv.edu>
License: MIT License
Project-URL: Repository, https://github.com/VSPEC-collab/vspec-vsm
Project-URL: Issues, https://github.com/VSPEC-collab/vspec-vsm/issues
Keywords: astronomy,star
Classifier: Development Status :: 4 - Beta
Classifier: Intended Audience :: Science/Research
Classifier: Topic :: Scientific/Engineering :: Astronomy
Classifier: License :: OSI Approved :: MIT License
Classifier: Programming Language :: Python :: 3
Classifier: Programming Language :: Python :: 3.9
Classifier: Programming Language :: Python :: 3.10
Classifier: Programming Language :: Python :: 3.11
Classifier: Operating System :: OS Independent
Requires-Python: >=3.9
License-File: LICENSE
Requires-Dist: astropy
Requires-Dist: numpy~=1.26
Requires-Dist: jax
Requires-Dist: tinygp
Provides-Extra: dev
Requires-Dist: pytest; extra == "dev"
Requires-Dist: pep8; extra == "dev"
Requires-Dist: furo==2023.9.10; extra == "dev"
Requires-Dist: numpydoc; extra == "dev"
Requires-Dist: sphinx; extra == "dev"
Requires-Dist: sphinx-automodapi; extra == "dev"
Requires-Dist: sphinx-gallery; extra == "dev"
Requires-Dist: sphinxcontrib-bibtex; extra == "dev"
Requires-Dist: sphinxcontrib-napoleon; extra == "dev"
Provides-Extra: plot
Requires-Dist: matplotlib; extra == "plot"
Requires-Dist: cartopy; extra == "plot"
